Workbook

Sheet Start Here
A1: Trading Comps — Guided Analysis
A2: Value SpaceX by analyzing how the market prices comparable public companies. You make the calls; the sheet does the math.
A4: This workbook walks you through a real comparable-companies (“comps”) analysis in nine steps. The calculations are automated, but the JUDGMENT is yours: which peers are truly comparable, which multiples to trust, and what range to conclude.
A6: The nine steps
B7: Step 1 | C7: Candidate peers — Start from PitchBook’s suggested companies; add any others worth considering.
B8: Step 2 | C8: SpaceX snapshot — Understand the target: its business, end markets and financials (filled in for you).
B9: Step 3 | C9: Screen peers — Score each candidate on business-model and end-market fit; decide who to include.
B10: Step 4 | C10: Market data — Pull share price, shares, cash and debt for the peers you kept; market cap & TEV auto-calc.
B11: Step 5 | C11: Multiples & ratios — Enter peer financials; every valuation multiple and operating ratio calculates automatically.
B12: Step 6 | C12: Select multiples — The sheet flags which multiples look most usable; you choose the ones to rely on.
B13: Step 7 | C13: Apply to SpaceX — Your selected multiples are applied to SpaceX’s metrics to imply a value.
B14: Step 8 | C14: Valuation range — Combine the methods into a low–base–high range and compare to the IPO price.
B15: Step 9 | C15: Conclusion — Write up your conclusion, what drove it, and the key caveats.
A17: Color key
B18: Yellow | C18: You type here — your data, scores or decisions.
B19: Green / black | C19: Calculates automatically. Don’t overwrite.
B20: Grey | C20: A note or instruction to read.

Sheet Step 1 - Candidate Peers
A1: Step 1 — Candidate Peers
A2: Cast a wide net first. You’ll narrow the list in Step 3.
A4: PitchBook flagged the companies below as most similar to SpaceX. Add any other public companies you think could be relevant (e.g., satellite-broadband, aerospace & defense, or high-growth tech names). Don’t screen yet — just brainstorm.
A6: ▶ YOUR TURN: Review the suggested names and add your own candidates in the blank rows.
A7: Company | B7: What they do | C7: Why it might be comparable | D7: Your idea? (add notes)
A8: Rocket Lab | B8: Small/medium launch + space systems | C8: Closest pure-play launch + space peer
A9: L3Harris | B9: Aerospace Developer / Defense | C9: Public space company; different model
A10: Firefly Aerospace | B10: Space / Defemse Tech / Launch Vehicles | C10: Just went public / SpaceX competitor
A11: Planet Labs | B11: Satellite imaging | C11: Space infrastructure
A12: Lockheed Martin | B12: Aerospace / Defense / Space Systems | C12: Large government space company
A13: Northrop Grumman | B13: Aeronautical / Space / Defense Systems | C13: Publicly held; space systems manufacturer
A14: Boeing | B14: Aerospace / defense / space manufacturer | C14: publicly held; aerospace manufacturer
A15: Intuitive Machines | B15: Space infrastructure and services | C15: Space network connectivity and space tech developer
A16: AST Space Mobile | B16: Communication equipment / telecom service provider | C16: they are space tech and telecom service manufacturer
A17: ViaSat | B17: Communications / Internet Connectivity | C17: Comparable to Starlink
A18: Tip: think across SpaceX’s three businesses — launch/space, Starlink broadband (a connectivity / telecom-like business), and AI (xAI). The best peer set may span more than one industry.

Sheet Step 2 - SpaceX Snapshot
A1: Step 2 — SpaceX Snapshot ($ in millions)
A2: Know your target before you value it. Figures are from the provided sources (LTM).
A4: Business model & end markets
A5: Three businesses: (1) Space — rocket launch and Starship; (2) Connectivity — Starlink satellite broadband (the largest share of revenue); (3) AI — xAI.
A6: Stage: high-growth and generating substantial revenue, but NOT consistently profitable yet (heavy reinvestment / capex).
A7: End markets: commercial & government launch, consumer/enterprise/government broadband, and AI compute.
A8: Founded 2002 · ~22,000 employees · currently filing to go public (IPO).
A10: Key financials (LTM) — used by later steps
A11: Metric | B11: Value | C11: Sign | D11: Note
A12: Revenue | B12: 19301 | C12: =IF($B12="","",IF($B12>0,"positive","negative")) -> positive | D12: Top line; positive
A13: Gross profit | B13: 9424 | C13: =IF($B13="","",IF($B13>0,"positive","negative")) -> positive | D13: Revenue minus direct costs
A14: EBITDA (adjusted) | B14: 1299 | C14: =IF($B14="","",IF($B14>0,"positive","negative")) -> positive | D14: Positive on an adjusted basis
A15: EBIT (adjusted) | B15: -6401 | C15: =IF($B15="","",IF($B15>0,"positive","negative")) -> negative | D15: Negative → earnings multiples likely NM
A16: Net income | B16: -6792 | C16: =IF($B16="","",IF($B16>0,"positive","negative")) -> negative | D16: Negative → P/E not meaningful
A17: Free cash flow | B17: -21629 | C17: =IF($B17="","",IF($B17>0,"positive","negative")) -> negative | D17: Negative → heavy capex / reinvestment
A18: Net debt (debt − cash) | B18: 6928 | C18: =IF($B18="","",IF($B18>0,"positive","negative")) -> positive | D18: Subtracted to get equity value
A19: Diluted shares (mm) | B19: 13075.9 | C19: =IF($B19="","",IF($B19>0,"positive","negative")) -> positive | D19: Used to convert equity value to a price
A20: FY+1 Revenue (your estimate) | B20: 23903 | C20: =IF($B20="","",IF($B20>0,"positive","negative")) -> positive | D20: Sources don’t give this — enter your own forecast
A21: FY+1 EBITDA (your estimate) | B21: 7405 | C21: =IF($B21="","",IF($B21>0,"positive","negative")) -> positive | D21: Optional; for forward multiples
A23: Context ratios (auto)
A24: Gross margin | B24: =IF($B$12=0,"",$B$13/$B$12) -> 0.48826486 | D24: Healthy and improving
A25: EBITDA margin (adjusted) | B25: =IF($B$12=0,"",$B$14/$B$12) -> 0.067302212 | D25: Positive on adjusted basis
A27: Memo: IPO offer price ($/share) | B27: 135 | D27: Compare your conclusion to this in Step 8
A29: Notice already: EBIT, net income and free cash flow are NEGATIVE. That’s a strong hint that EBIT, P/E and FCF multiples will be ‘not meaningful’ for SpaceX — Step 6 will flag this for you automatically.

Sheet Step 3 - Screen Peers
A1: Step 3 — Screen Peers by Business Model & End Market
A2: Score 1–5 (1 = weak fit, 5 = strong fit). The weighted score and a suggestion calculate automatically; the Include call is yours.
A4: This is the most important judgment in the whole analysis. A famous company is not automatically a good comp — and a PRIVATE company can’t be used (no share price). Weight the criteria (yellow row) to reflect what matters most for SpaceX; weights should sum to 100%.
D6: Weights → | E6: 0.25 | F6: 0.25 | G6: 0.25 | H6: 0.25 | I6: =SUM(E6:H6) -> 1 | J6: ← must = 100%
A7: ▶ YOUR TURN: Classify each peer’s end market, check if it’s public, score the four fit criteria 1–5, then decide Include Yes/No.
A8: Company | B8: Business description | C8: Primary end market | D8: Public? Ticker | E8: Business-model fit | F8: End-market fit | G8: Size / stage fit | H8: Public & data available | I8: Comparability score | J8: Suggestion (auto) | K8: Include? (Yes/No) | L8: Notes
A9: Rocket Lab | B9: Launch + space systems | C9: Government or commerical satellite launch | D9: RKLB | E9: 5 | F9: 4 | G9: 3 | H9: 5 | I9: =IF($A9="","",IF(COUNT(E9:H9)=0,"",SUMPRODUCT(E9:H9,E$6:H$6))) -> 4.25 | J9: =IF(I9="","",IF(I9>=3.5,"Consider including",IF(I9>=2.5,"Borderline","Likely exclude"))) -> Consider including | K9: Yes
A10: L3Harris | B10: Aerospace Developer / Defense | C10: Government / National Security Launch | D10: LHX | E10: 3 | F10: 3 | G10: 4 | H10: 5 | I10: =IF($A10="","",IF(COUNT(E10:H10)=0,"",SUMPRODUCT(E10:H10,E$6:H$6))) -> 3.75 | J10: =IF(I10="","",IF(I10>=3.5,"Consider including",IF(I10>=2.5,"Borderline","Likely exclude"))) -> Consider including | K10: Yes
A11: Firefly | B11: Space / Defemse Tech / Launch Vehicles | C11: Government / defense / national security space | D11: FLY | E11: 3 | F11: 4 | G11: 4 | H11: 5 | I11: =IF($A11="","",IF(COUNT(E11:H11)=0,"",SUMPRODUCT(E11:H11,E$6:H$6))) -> 4 | J11: =IF(I11="","",IF(I11>=3.5,"Consider including",IF(I11>=2.5,"Borderline","Likely exclude"))) -> Consider including | K11: Yes
A12: Planet Labs | B12: Satellite imaging | C12: Commercial and government Earth observation / satellite data | D12: PL | E12: 3 | F12: 4 | G12: 2 | H12: 5 | I12: =IF($A12="","",IF(COUNT(E12:H12)=0,"",SUMPRODUCT(E12:H12,E$6:H$6))) -> 3.5 | J12: =IF(I12="","",IF(I12>=3.5,"Consider including",IF(I12>=2.5,"Borderline","Likely exclude"))) -> Consider including | K12: Yes
A13: Lockheed Martin | B13: Aerospace / Defense / Space Systems | C13: Government / defense / space systems | D13: LMT | E13: 2 | F13: 3 | G13: 2 | H13: 5 | I13: =IF($A13="","",IF(COUNT(E13:H13)=0,"",SUMPRODUCT(E13:H13,E$6:H$6))) -> 3 | J13: =IF(I13="","",IF(I13>=3.5,"Consider including",IF(I13>=2.5,"Borderline","Likely exclude"))) -> Borderline | K13: No
A14: Northrop Grumman | B14: Aeronautical / Space / Defense Systems | C14: Government / defense / national security space | D14: NOC | E14: 3 | F14: 3 | G14: 4 | H14: 5 | I14: =IF($A14="","",IF(COUNT(E14:H14)=0,"",SUMPRODUCT(E14:H14,E$6:H$6))) -> 3.75 | J14: =IF(I14="","",IF(I14>=3.5,"Consider including",IF(I14>=2.5,"Borderline","Likely exclude"))) -> Consider including | K14: Yes
A15: Boeing | B15: Aerospace / defense / space manufacturer | C15: Government / defense | D15: BA | E15: 3 | F15: 2 | G15: 2 | H15: 5 | I15: =IF($A15="","",IF(COUNT(E15:H15)=0,"",SUMPRODUCT(E15:H15,E$6:H$6))) -> 3 | J15: =IF(I15="","",IF(I15>=3.5,"Consider including",IF(I15>=2.5,"Borderline","Likely exclude"))) -> Borderline | K15: No
A16: Intuitive Machines | B16: Space infrastructure and services | C16: Nasa services / lunar exploration | D16: LUNR | E16: 5 | F16: 5 | G16: 1 | H16: 5 | I16: =IF($A16="","",IF(COUNT(E16:H16)=0,"",SUMPRODUCT(E16:H16,E$6:H$6))) -> 4 | J16: =IF(I16="","",IF(I16>=3.5,"Consider including",IF(I16>=2.5,"Borderline","Likely exclude"))) -> Consider including | K16: Yes
A17: AST Space Mobile | B17: Communication equipment / telecom service provider | C17: Satellite to cellular telecom | D17: ASTS | E17: 4 | F17: 5 | G17: 2 | H17: 5 | I17: =IF($A17="","",IF(COUNT(E17:H17)=0,"",SUMPRODUCT(E17:H17,E$6:H$6))) -> 4 | J17: =IF(I17="","",IF(I17>=3.5,"Consider including",IF(I17>=2.5,"Borderline","Likely exclude"))) -> Consider including | K17: Yes
A18: ViaStat | B18: Communications / Internet Connectivity | C18: satellite broadband to commercial & government | D18: VSAT | E18: 3 | F18: 4 | G18: 3 | H18: 5 | I18: =IF($A18="","",IF(COUNT(E18:H18)=0,"",SUMPRODUCT(E18:H18,E$6:H$6))) -> 3.75 | J18: =IF(I18="","",IF(I18>=3.5,"Consider including",IF(I18>=2.5,"Borderline","Likely exclude"))) -> Consider including | K18: Yes
I20: =IF($A20="","",IF(COUNT(E20:H20)=0,"",SUMPRODUCT(E20:H20,E$6:H$6))) | J20: =IF(I20="","",IF(I20>=3.5,"Consider including",IF(I20>=2.5,"Borderline","Likely exclude")))
A22: The ‘Suggestion’ column is only a nudge from your own scores — you make the final Include call and explain it in Notes. Keep the SAME row order on Steps 4 and 5 so everything lines up.

Sheet Step 4 - Market Data
A1: Step 4 — Pull Public Market Data
A2: Only for peers you marked Include = Yes. Market cap and TEV calculate automatically.
A4: TEV (Total Enterprise Value) = Market cap + Total debt + Preferred + Minority − Cash. Market cap = Share price × diluted shares. Use ONE consistent date across all peers. Leave a row blank if you excluded that company.
A6: ▶ YOUR TURN: Enter share price, diluted shares, cash and debt for each INCLUDED peer (as of one date).
A7: Company | B7: Include? | C7: Ticker | D7: Share price ($) | E7: Diluted shares (mm) | F7: Market cap | G7: Cash | H7: Total debt | I7: Pref. + minority | J7: TEV | K7: Data date
A8: =IF('Step 3 - Screen Peers'!A8="","",'Step 3 - Screen Peers'!A8) -> Company | B8: =IF('Step 3 - Screen Peers'!K8="","",'Step 3 - Screen Peers'!K8) -> Include? (Yes/No) | C8: =IF('Step 3 - Screen Peers'!D8="","",'Step 3 - Screen Peers'!D8) -> Public? Ticker | F8: =IF(OR($D8="",$E8=""),"",$D8*$E8) | J8: =IF($F8="","",$F8+N($H8)+N($I8)-N($G8))
A9: =IF('Step 3 - Screen Peers'!A9="","",'Step 3 - Screen Peers'!A9) -> Rocket Lab | B9: =IF('Step 3 - Screen Peers'!K9="","",'Step 3 - Screen Peers'!K9) -> Yes | C9: =IF('Step 3 - Screen Peers'!D9="","",'Step 3 - Screen Peers'!D9) -> RKLB | D9: 108.23 | E9: 555.6 | F9: =IF(OR($D9="",$E9=""),"",$D9*$E9) -> 60132.588 | G9: 1211 | H9: 138.7 | I9: 0 | J9: =IF($F9="","",$F9+N($H9)+N($I9)-N($G9)) -> 59060.288 | K9: 46112
A10: =IF('Step 3 - Screen Peers'!A10="","",'Step 3 - Screen Peers'!A10) -> L3Harris | B10: No | C10: =IF('Step 3 - Screen Peers'!D10="","",'Step 3 - Screen Peers'!D10) -> LHX | D10: 308.17 | E10: 188.15 | F10: =IF(OR($D10="",$E10=""),"",$D10*$E10) -> 57982.185 | G10: 590 | H10: 11357 | I10: 0 | J10: =IF($F10="","",$F10+N($H10)+N($I10)-N($G10)) -> 68749.186 | K10: 46112
A11: =IF('Step 3 - Screen Peers'!A11="","",'Step 3 - Screen Peers'!A11) -> Firefly | B11: =IF('Step 3 - Screen Peers'!K11="","",'Step 3 - Screen Peers'!K11) -> Yes | C11: =IF('Step 3 - Screen Peers'!D11="","",'Step 3 - Screen Peers'!D11) -> FLY | D11: 33.45 | E11: 109.081 | F11: =IF(OR($D11="",$E11=""),"",$D11*$E11) -> 3648.7595 | G11: 326.179 | H11: 52.99 | I11: 0 | J11: =IF($F11="","",$F11+N($H11)+N($I11)-N($G11)) -> 3375.5705 | K11: 46112
A12: =IF('Step 3 - Screen Peers'!A12="","",'Step 3 - Screen Peers'!A12) -> Planet Labs | B12: =IF('Step 3 - Screen Peers'!K12="","",'Step 3 - Screen Peers'!K12) -> Yes | C12: =IF('Step 3 - Screen Peers'!D12="","",'Step 3 - Screen Peers'!D12) -> PL | D12: 31.17 | E12: 300.267 | F12: =IF(OR($D12="",$E12=""),"",$D12*$E12) -> 9359.3224 | G12: 375.596 | H12: 488.035 | I12: 0 | J12: =IF($F12="","",$F12+N($H12)+N($I12)-N($G12)) -> 9471.7614 | K12: 46142
A13: =IF('Step 3 - Screen Peers'!A13="","",'Step 3 - Screen Peers'!A13) -> Lockheed Martin | B13: =IF('Step 3 - Screen Peers'!K13="","",'Step 3 - Screen Peers'!K13) -> No | C13: =IF('Step 3 - Screen Peers'!D13="","",'Step 3 - Screen Peers'!D13) -> LMT | D13: 530.13 | E13: 232.45 | F13: =IF(OR($D13="",$E13=""),"",$D13*$E13) -> 123228.72 | G13: 1894 | H13: 20697 | I13: 50 | J13: =IF($F13="","",$F13+N($H13)+N($I13)-N($G13)) -> 142081.72 | K13: 46112
A14: =IF('Step 3 - Screen Peers'!A14="","",'Step 3 - Screen Peers'!A14) -> Northrop Grumman | B14: =IF('Step 3 - Screen Peers'!K14="","",'Step 3 - Screen Peers'!K14) -> Yes | C14: =IF('Step 3 - Screen Peers'!D14="","",'Step 3 - Screen Peers'!D14) -> NOC | D14: 548.67 | E14: 143.2 | F14: =IF(OR($D14="",$E14=""),"",$D14*$E14) -> 78569.544 | G14: 2090 | H14: 16316 | I14: 0 | J14: =IF($F14="","",$F14+N($H14)+N($I14)-N($G14)) -> 92795.544 | K14: 46112
A15: =IF('Step 3 - Screen Peers'!A15="","",'Step 3 - Screen Peers'!A15) -> Boeing | B15: No | C15: =IF('Step 3 - Screen Peers'!D15="","",'Step 3 - Screen Peers'!D15) -> BA | D15: 214.51 | E15: 770.9 | F15: =IF(OR($D15="",$E15=""),"",$D15*$E15) -> 165365.76 | G15: 9441 | H15: 47209 | I15: 352 | J15: =IF($F15="","",$F15+N($H15)+N($I15)-N($G15)) -> 203485.76 | K15: 46112
A16: =IF('Step 3 - Screen Peers'!A16="","",'Step 3 - Screen Peers'!A16) -> Intuitive Machines | B16: Yes | C16: =IF('Step 3 - Screen Peers'!D16="","",'Step 3 - Screen Peers'!D16) -> LUNR | D16: 27.47 | E16: 125.6 | F16: =IF(OR($D16="",$E16=""),"",$D16*$E16) -> 3450.232 | G16: 243.4 | H16: 426.4 | I16: 7.7 | J16: =IF($F16="","",$F16+N($H16)+N($I16)-N($G16)) -> 3640.932 | K16: 46112
A17: =IF('Step 3 - Screen Peers'!A17="","",'Step 3 - Screen Peers'!A17) -> AST Space Mobile | B17: =IF('Step 3 - Screen Peers'!K17="","",'Step 3 - Screen Peers'!K17) -> Yes | C17: =IF('Step 3 - Screen Peers'!D17="","",'Step 3 - Screen Peers'!D17) -> ASTS | D17: 88.71 | E17: 272.661 | F17: =IF(OR($D17="",$E17=""),"",$D17*$E17) -> 24187.757 | G17: 3458.9 | H17: 2991.4 | I17: 0 | J17: =IF($F17="","",$F17+N($H17)+N($I17)-N($G17)) -> 23720.257 | K17: 46112
A18: =IF('Step 3 - Screen Peers'!A18="","",'Step 3 - Screen Peers'!A18) -> ViaStat | B18: =IF('Step 3 - Screen Peers'!K18="","",'Step 3 - Screen Peers'!K18) -> Yes | C18: =IF('Step 3 - Screen Peers'!D18="","",'Step 3 - Screen Peers'!D18) -> VSAT | D18: 63.94 | E18: 134.7 | F18: =IF(OR($D18="",$E18=""),"",$D18*$E18) -> 8612.718 | G18: 1746.8 | H18: 6939.6 | I18: 0 | J18: =IF($F18="","",$F18+N($H18)+N($I18)-N($G18)) -> 13805.518 | K18: 46112

Sheet Step 5 - Multiples & Ratios
A1: Step 5 — Calculate Valuation Multiples & Operating Ratios ($mm)
A2: Enter each peer’s financials (yellow). Every multiple and ratio to the right calculates automatically.
A4: Company, Include, TEV and Market cap are linked from earlier steps. Enter the income-statement / cash-flow figures (yellow). A multiple shows ‘NM’ (not meaningful) whenever its denominator is zero or negative — watch how often that happens for the profit-based multiples; that’s a real signal about which multiples to trust.
A6: Company | B6: Inc? | C6: TEV | D6: Mkt cap | E6: Revenue | F6: Gross profit | G6: EBITDA | H6: EBIT | I6: Net income | J6: FCF | K6: FY+1 Rev | L6: FY+1 EBITDA | M6: TEV / Rev | N6: TEV / Gross | O6: TEV / EBITDA | P6: TEV / EBIT | Q6: P / E | R6: TEV / FCF | S6: TEV / Rev (FY+1) | T6: TEV / EBITDA (FY+1) | U6: Rev gth (FY+1) | V6: Gross mgn | W6: EBITDA mgn | X6: EBIT mgn | Y6: FCF mgn
A7: =IF('Step 4 - Market Data'!A8="","",'Step 4 - Market Data'!A8) -> Company | B7: =IF('Step 4 - Market Data'!B8="","",'Step 4 - Market Data'!B8) -> Include? (Yes/No) | C7: =IF('Step 4 - Market Data'!J8="","",'Step 4 - Market Data'!J8) | D7: =IF('Step 4 - Market Data'!F8="","",'Step 4 - Market Data'!F8) | M7: =IF($C7="","",IF(OR($E7="",$E7<=0),"NM",$C7/$E7)) | N7: =IF($C7="","",IF(OR($F7="",$F7<=0),"NM",$C7/$F7)) | O7: =IF($C7="","",IF(OR($G7="",$G7<=0),"NM",$C7/$G7)) | P7: =IF($C7="","",IF(OR($H7="",$H7<=0),"NM",$C7/$H7)) | Q7: =IF($D7="","",IF(OR($I7="",$I7<=0),"NM",$D7/$I7)) | R7: =IF($C7="","",IF(OR($J7="",$J7<=0),"NM",$C7/$J7)) | S7: =IF($C7="","",IF(OR($K7="",$K7<=0),"NM",$C7/$K7)) | T7: =IF($C7="","",IF(OR($L7="",$L7<=0),"NM",$C7/$L7)) | U7: =IF(OR($E7="",$K7=""),"",IF($E7<=0,"NM",$K7/$E7-1)) | V7: =IF(OR($E7="",$F7=""),"",IF($E7<=0,"NM",$F7/$E7)) | W7: =IF(OR($E7="",$G7=""),"",IF($E7<=0,"NM",$G7/$E7)) | X7: =IF(OR($E7="",$H7=""),"",IF($E7<=0,"NM",$H7/$E7)) | Y7: =IF(OR($E7="",$J7=""),"",IF($E7<=0,"NM",$J7/$E7))
A8: =IF('Step 4 - Market Data'!A9="","",'Step 4 - Market Data'!A9) -> Rocket Lab | B8: =IF('Step 4 - Market Data'!B9="","",'Step 4 - Market Data'!B9) -> Yes | C8: =IF('Step 4 - Market Data'!J9="","",'Step 4 - Market Data'!J9) -> 59060.288 | D8: =IF('Step 4 - Market Data'!F9="","",'Step 4 - Market Data'!F9) -> 60132.588 | E8: 680 | F8: 248 | G8: -82.979 | H8: -139.5 | I8: -112 | J8: -207 | K8: 851 | L8: -47 | M8: =IF($C8="","",IF(OR($E8="",$E8<=0),"NM",$C8/$E8)) -> 86.853365 | N8: =IF($C8="","",IF(OR($F8="",$F8<=0),"NM",$C8/$F8)) -> 238.14632 | O8: =IF($C8="","",IF(OR($G8="",$G8<=0),"NM",$C8/$G8)) -> NM | P8: =IF($C8="","",IF(OR($H8="",$H8<=0),"NM",$C8/$H8)) -> NM | Q8: =IF($D8="","",IF(OR($I8="",$I8<=0),"NM",$D8/$I8)) -> NM | R8: =IF($C8="","",IF(OR($J8="",$J8<=0),"NM",$C8/$J8)) -> NM | S8: =IF($C8="","",IF(OR($K8="",$K8<=0),"NM",$C8/$K8)) -> 69.401043 | T8: =IF($C8="","",IF(OR($L8="",$L8<=0),"NM",$C8/$L8)) -> NM | U8: =IF(OR($E8="",$K8=""),"",IF($E8<=0,"NM",$K8/$E8-1)) -> 0.25147059 | V8: =IF(OR($E8="",$F8=""),"",IF($E8<=0,"NM",$F8/$E8)) -> 0.36470588 | W8: =IF(OR($E8="",$G8=""),"",IF($E8<=0,"NM",$G8/$E8)) -> -0.12202794 | X8: =IF(OR($E8="",$H8=""),"",IF($E8<=0,"NM",$H8/$E8)) -> -0.20514706 | Y8: =IF(OR($E8="",$J8=""),"",IF($E8<=0,"NM",$J8/$E8)) -> -0.30441176
A9: =IF('Step 4 - Market Data'!A10="","",'Step 4 - Market Data'!A10) -> L3Harris | B9: Yes | C9: =IF('Step 4 - Market Data'!J10="","",'Step 4 - Market Data'!J10) -> 68749.186 | D9: =IF('Step 4 - Market Data'!F10="","",'Step 4 - Market Data'!F10) -> 57982.185 | E9: 22477 | F9: 5677 | G9: 4208 | H9: 3003 | I9: 2046.309 | J9: 3438.697 | K9: 23250 | L9: 4050 | M9: =IF($C9="","",IF(OR($E9="",$E9<=0),"NM",$C9/$E9)) -> 3.058646 | N9: =IF($C9="","",IF(OR($F9="",$F9<=0),"NM",$C9/$F9)) -> 12.110126 | O9: =IF($C9="","",IF(OR($G9="",$G9<=0),"NM",$C9/$G9)) -> 16.337734 | P9: =IF($C9="","",IF(OR($H9="",$H9<=0),"NM",$C9/$H9)) -> 22.893502 | Q9: =IF($D9="","",IF(OR($I9="",$I9<=0),"NM",$D9/$I9)) -> 28.33501 | R9: =IF($C9="","",IF(OR($J9="",$J9<=0),"NM",$C9/$J9)) -> 19.992801 | S9: =IF($C9="","",IF(OR($K9="",$K9<=0),"NM",$C9/$K9)) -> 2.9569542 | T9: =IF($C9="","",IF(OR($L9="",$L9<=0),"NM",$C9/$L9)) -> 16.975108 | U9: =IF(OR($E9="",$K9=""),"",IF($E9<=0,"NM",$K9/$E9-1)) -> 0.03439071 | V9: =IF(OR($E9="",$F9=""),"",IF($E9<=0,"NM",$F9/$E9)) -> 0.25256929 | W9: =IF(OR($E9="",$G9=""),"",IF($E9<=0,"NM",$G9/$E9)) -> 0.1872136 | X9: =IF(OR($E9="",$H9=""),"",IF($E9<=0,"NM",$H9/$E9)) -> 0.13360324 | Y9: =IF(OR($E9="",$J9=""),"",IF($E9<=0,"NM",$J9/$E9)) -> 0.15298736
A10: =IF('Step 4 - Market Data'!A11="","",'Step 4 - Market Data'!A11) -> Firefly | B10: =IF('Step 4 - Market Data'!B11="","",'Step 4 - Market Data'!B11) -> Yes | C10: =IF('Step 4 - Market Data'!J11="","",'Step 4 - Market Data'!J11) -> 3375.5705 | D10: =IF('Step 4 - Market Data'!F11="","",'Step 4 - Market Data'!F11) -> 3648.7595 | E10: 184.879 | F10: 45.907 | G10: -216 | H10: -271 | I10: -240.747 | J10: -265.823 | K10: 435 | L10: -50 | M10: =IF($C10="","",IF(OR($E10="",$E10<=0),"NM",$C10/$E10)) -> 18.258269 | N10: =IF($C10="","",IF(OR($F10="",$F10<=0),"NM",$C10/$F10)) -> 73.530626 | O10: =IF($C10="","",IF(OR($G10="",$G10<=0),"NM",$C10/$G10)) -> NM | P10: =IF($C10="","",IF(OR($H10="",$H10<=0),"NM",$C10/$H10)) -> NM | Q10: =IF($D10="","",IF(OR($I10="",$I10<=0),"NM",$D10/$I10)) -> NM | R10: =IF($C10="","",IF(OR($J10="",$J10<=0),"NM",$C10/$J10)) -> NM | S10: =IF($C10="","",IF(OR($K10="",$K10<=0),"NM",$C10/$K10)) -> 7.7599321 | T10: =IF($C10="","",IF(OR($L10="",$L10<=0),"NM",$C10/$L10)) -> NM | U10: =IF(OR($E10="",$K10=""),"",IF($E10<=0,"NM",$K10/$E10-1)) -> 1.3528903 | V10: =IF(OR($E10="",$F10=""),"",IF($E10<=0,"NM",$F10/$E10)) -> 0.24830835 | W10: =IF(OR($E10="",$G10=""),"",IF($E10<=0,"NM",$G10/$E10)) -> -1.1683317 | X10: =IF(OR($E10="",$H10=""),"",IF($E10<=0,"NM",$H10/$E10)) -> -1.4658236 | Y10: =IF(OR($E10="",$J10=""),"",IF($E10<=0,"NM",$J10/$E10)) -> -1.4378215
A11: =IF('Step 4 - Market Data'!A12="","",'Step 4 - Market Data'!A12) -> Planet Labs | B11: =IF('Step 4 - Market Data'!B12="","",'Step 4 - Market Data'!B12) -> Yes | C11: =IF('Step 4 - Market Data'!J12="","",'Step 4 - Market Data'!J12) -> 9471.7614 | D11: =IF('Step 4 - Market Data'!F12="","",'Step 4 - Market Data'!F12) -> 9359.3224 | E11: 335.612 | F11: 186.283 | G11: 13 | H11: -44 | I11: -18.706 | J11: -85.04 | K11: 390 | L11: 25 | M11: =IF($C11="","",IF(OR($E11="",$E11<=0),"NM",$C11/$E11)) -> 28.222356 | N11: =IF($C11="","",IF(OR($F11="",$F11<=0),"NM",$C11/$F11)) -> 50.846086 | O11: =IF($C11="","",IF(OR($G11="",$G11<=0),"NM",$C11/$G11)) -> 728.59703 | P11: =IF($C11="","",IF(OR($H11="",$H11<=0),"NM",$C11/$H11)) -> NM | Q11: =IF($D11="","",IF(OR($I11="",$I11<=0),"NM",$D11/$I11)) -> NM | R11: =IF($C11="","",IF(OR($J11="",$J11<=0),"NM",$C11/$J11)) -> NM | S11: =IF($C11="","",IF(OR($K11="",$K11<=0),"NM",$C11/$K11)) -> 24.286568 | T11: =IF($C11="","",IF(OR($L11="",$L11<=0),"NM",$C11/$L11)) -> 378.87046 | U11: =IF(OR($E11="",$K11=""),"",IF($E11<=0,"NM",$K11/$E11-1)) -> 0.16205618 | V11: =IF(OR($E11="",$F11=""),"",IF($E11<=0,"NM",$F11/$E11)) -> 0.55505465 | W11: =IF(OR($E11="",$G11=""),"",IF($E11<=0,"NM",$G11/$E11)) -> 0.038735206 | X11: =IF(OR($E11="",$H11=""),"",IF($E11<=0,"NM",$H11/$E11)) -> -0.13110377 | Y11: =IF(OR($E11="",$J11=""),"",IF($E11<=0,"NM",$J11/$E11)) -> -0.25338784
A12: =IF('Step 4 - Market Data'!A13="","",'Step 4 - Market Data'!A13) -> Lockheed Martin | B12: =IF('Step 4 - Market Data'!B13="","",'Step 4 - Market Data'!B13) -> No | C12: =IF('Step 4 - Market Data'!J13="","",'Step 4 - Market Data'!J13) -> 142081.72 | D12: =IF('Step 4 - Market Data'!F13="","",'Step 4 - Market Data'!F13) -> 123228.72 | E12: 75106 | F12: 7374 | G12: 8794 | H12: 7106 | I12: 5069.91 | J12: 7917.591 | K12: 76500 | L12: 8800 | M12: =IF($C12="","",IF(OR($E12="",$E12<=0),"NM",$C12/$E12)) -> 1.8917492 | N12: =IF($C12="","",IF(OR($F12="",$F12<=0),"NM",$C12/$F12)) -> 19.26793 | O12: =IF($C12="","",IF(OR($G12="",$G12<=0),"NM",$C12/$G12)) -> 16.156666 | P12: =IF($C12="","",IF(OR($H12="",$H12<=0),"NM",$C12/$H12)) -> 19.994613 | Q12: =IF($D12="","",IF(OR($I12="",$I12<=0),"NM",$D12/$I12)) -> 24.305899 | R12: =IF($C12="","",IF(OR($J12="",$J12<=0),"NM",$C12/$J12)) -> 17.945069 | S12: =IF($C12="","",IF(OR($K12="",$K12<=0),"NM",$C12/$K12)) -> 1.8572774 | T12: =IF($C12="","",IF(OR($L12="",$L12<=0),"NM",$C12/$L12)) -> 16.14565 | U12: =IF(OR($E12="",$K12=""),"",IF($E12<=0,"NM",$K12/$E12-1)) -> 0.018560435 | V12: =IF(OR($E12="",$F12=""),"",IF($E12<=0,"NM",$F12/$E12)) -> 0.098181237 | W12: =IF(OR($E12="",$G12=""),"",IF($E12<=0,"NM",$G12/$E12)) -> 0.11708785 | X12: =IF(OR($E12="",$H12=""),"",IF($E12<=0,"NM",$H12/$E12)) -> 0.094612947 | Y12: =IF(OR($E12="",$J12=""),"",IF($E12<=0,"NM",$J12/$E12)) -> 0.10541889
A13: =IF('Step 4 - Market Data'!A14="","",'Step 4 - Market Data'!A14) -> Northrop Grumman | B13: No | C13: =IF('Step 4 - Market Data'!J14="","",'Step 4 - Market Data'!J14) -> 92795.544 | D13: =IF('Step 4 - Market Data'!F14="","",'Step 4 - Market Data'!F14) -> 78569.544 | E13: 42367 | F13: 8693 | G13: 7586 | H13: 6079 | I13: 4483 | J13: 5067 | K13: 43750 | L13: 6500 | M13: =IF($C13="","",IF(OR($E13="",$E13<=0),"NM",$C13/$E13)) -> 2.1902788 | N13: =IF($C13="","",IF(OR($F13="",$F13<=0),"NM",$C13/$F13)) -> 10.674743 | O13: =IF($C13="","",IF(OR($G13="",$G13<=0),"NM",$C13/$G13)) -> 12.232473 | P13: =IF($C13="","",IF(OR($H13="",$H13<=0),"NM",$C13/$H13)) -> 15.264936 | Q13: =IF($D13="","",IF(OR($I13="",$I13<=0),"NM",$D13/$I13)) -> 17.526108 | R13: =IF($C13="","",IF(OR($J13="",$J13<=0),"NM",$C13/$J13)) -> 18.313705 | S13: =IF($C13="","",IF(OR($K13="",$K13<=0),"NM",$C13/$K13)) -> 2.121041 | T13: =IF($C13="","",IF(OR($L13="",$L13<=0),"NM",$C13/$L13)) -> 14.276238 | U13: =IF(OR($E13="",$K13=""),"",IF($E13<=0,"NM",$K13/$E13-1)) -> 0.032643331 | V13: =IF(OR($E13="",$F13=""),"",IF($E13<=0,"NM",$F13/$E13)) -> 0.20518328 | W13: =IF(OR($E13="",$G13=""),"",IF($E13<=0,"NM",$G13/$E13)) -> 0.17905445 | X13: =IF(OR($E13="",$H13=""),"",IF($E13<=0,"NM",$H13/$E13)) -> 0.14348432 | Y13: =IF(OR($E13="",$J13=""),"",IF($E13<=0,"NM",$J13/$E13)) -> 0.1195978
A14: =IF('Step 4 - Market Data'!A15="","",'Step 4 - Market Data'!A15) -> Boeing | B14: =IF('Step 4 - Market Data'!B15="","",'Step 4 - Market Data'!B15) -> No | C14: =IF('Step 4 - Market Data'!J15="","",'Step 4 - Market Data'!J15) -> 203485.76 | D14: =IF('Step 4 - Market Data'!F15="","",'Step 4 - Market Data'!F15) -> 165365.76 | E14: 92184 | F14: 4418 | G14: 1864 | H14: 3924 | I14: -5778 | J14: 1006 | K14: 101100 | L14: 4600 | M14: =IF($C14="","",IF(OR($E14="",$E14<=0),"NM",$C14/$E14)) -> 2.207387 | N14: =IF($C14="","",IF(OR($F14="",$F14<=0),"NM",$C14/$F14)) -> 46.058343 | O14: =IF($C14="","",IF(OR($G14="",$G14<=0),"NM",$C14/$G14)) -> 109.16618 | P14: =IF($C14="","",IF(OR($H14="",$H14<=0),"NM",$C14/$H14)) -> 51.856717 | Q14: =IF($D14="","",IF(OR($I14="",$I14<=0),"NM",$D14/$I14)) -> NM | R14: =IF($C14="","",IF(OR($J14="",$J14<=0),"NM",$C14/$J14)) -> 202.27213 | S14: =IF($C14="","",IF(OR($K14="",$K14<=0),"NM",$C14/$K14)) -> 2.0127177 | T14: =IF($C14="","",IF(OR($L14="",$L14<=0),"NM",$C14/$L14)) -> 44.236035 | U14: =IF(OR($E14="",$K14=""),"",IF($E14<=0,"NM",$K14/$E14-1)) -> 0.096719604 | V14: =IF(OR($E14="",$F14=""),"",IF($E14<=0,"NM",$F14/$E14)) -> 0.047925887 | W14: =IF(OR($E14="",$G14=""),"",IF($E14<=0,"NM",$G14/$E14)) -> 0.020220429 | X14: =IF(OR($E14="",$H14=""),"",IF($E14<=0,"NM",$H14/$E14)) -> 0.04256704 | Y14: =IF(OR($E14="",$J14=""),"",IF($E14<=0,"NM",$J14/$E14)) -> 0.010912957
A15: =IF('Step 4 - Market Data'!A16="","",'Step 4 - Market Data'!A16) -> Intuitive Machines | B15: =IF('Step 4 - Market Data'!B16="","",'Step 4 - Market Data'!B16) -> Yes | C15: =IF('Step 4 - Market Data'!J16="","",'Step 4 - Market Data'!J16) -> 3640.932 | D15: =IF('Step 4 - Market Data'!F16="","",'Step 4 - Market Data'!F16) -> 3450.232 | E15: 328 | F15: 26 | G15: -54.9 | H15: -97.8 | I15: -121 | J15: -122 | K15: 950 | L15: 15 | M15: =IF($C15="","",IF(OR($E15="",$E15<=0),"NM",$C15/$E15)) -> 11.100402 | N15: =IF($C15="","",IF(OR($F15="",$F15<=0),"NM",$C15/$F15)) -> 140.03585 | O15: =IF($C15="","",IF(OR($G15="",$G15<=0),"NM",$C15/$G15)) -> NM | P15: =IF($C15="","",IF(OR($H15="",$H15<=0),"NM",$C15/$H15)) -> NM | Q15: =IF($D15="","",IF(OR($I15="",$I15<=0),"NM",$D15/$I15)) -> NM | R15: =IF($C15="","",IF(OR($J15="",$J15<=0),"NM",$C15/$J15)) -> NM | S15: =IF($C15="","",IF(OR($K15="",$K15<=0),"NM",$C15/$K15)) -> 3.83256 | T15: =IF($C15="","",IF(OR($L15="",$L15<=0),"NM",$C15/$L15)) -> 242.7288 | U15: =IF(OR($E15="",$K15=""),"",IF($E15<=0,"NM",$K15/$E15-1)) -> 1.8963415 | V15: =IF(OR($E15="",$F15=""),"",IF($E15<=0,"NM",$F15/$E15)) -> 0.079268293 | W15: =IF(OR($E15="",$G15=""),"",IF($E15<=0,"NM",$G15/$E15)) -> -0.16737805 | X15: =IF(OR($E15="",$H15=""),"",IF($E15<=0,"NM",$H15/$E15)) -> -0.29817073 | Y15: =IF(OR($E15="",$J15=""),"",IF($E15<=0,"NM",$J15/$E15)) -> -0.37195122
A16: =IF('Step 4 - Market Data'!A17="","",'Step 4 - Market Data'!A17) -> AST Space Mobile | B16: Yes | C16: =IF('Step 4 - Market Data'!J17="","",'Step 4 - Market Data'!J17) -> 23720.257 | D16: =IF('Step 4 - Market Data'!F17="","",'Step 4 - Market Data'!F17) -> 24187.757 | E16: 85 | F16: 49.7 | G16: -429 | H16: -486.9 | I16: -214 | J16: -340 | K16: 175 | L16: -580 | M16: =IF($C16="","",IF(OR($E16="",$E16<=0),"NM",$C16/$E16)) -> 279.06185 | N16: =IF($C16="","",IF(OR($F16="",$F16<=0),"NM",$C16/$F16)) -> 477.26876 | O16: =IF($C16="","",IF(OR($G16="",$G16<=0),"NM",$C16/$G16)) -> NM | P16: =IF($C16="","",IF(OR($H16="",$H16<=0),"NM",$C16/$H16)) -> NM | Q16: =IF($D16="","",IF(OR($I16="",$I16<=0),"NM",$D16/$I16)) -> NM | R16: =IF($C16="","",IF(OR($J16="",$J16<=0),"NM",$C16/$J16)) -> NM | S16: =IF($C16="","",IF(OR($K16="",$K16<=0),"NM",$C16/$K16)) -> 135.54433 | T16: =IF($C16="","",IF(OR($L16="",$L16<=0),"NM",$C16/$L16)) -> NM | U16: =IF(OR($E16="",$K16=""),"",IF($E16<=0,"NM",$K16/$E16-1)) -> 1.0588235 | V16: =IF(OR($E16="",$F16=""),"",IF($E16<=0,"NM",$F16/$E16)) -> 0.58470588 | W16: =IF(OR($E16="",$G16=""),"",IF($E16<=0,"NM",$G16/$E16)) -> -5.0470588 | X16: =IF(OR($E16="",$H16=""),"",IF($E16<=0,"NM",$H16/$E16)) -> -5.7282353 | Y16: =IF(OR($E16="",$J16=""),"",IF($E16<=0,"NM",$J16/$E16)) -> -4
A17: =IF('Step 4 - Market Data'!A18="","",'Step 4 - Market Data'!A18) -> ViaStat | B17: =IF('Step 4 - Market Data'!B18="","",'Step 4 - Market Data'!B18) -> Yes | C17: =IF('Step 4 - Market Data'!J18="","",'Step 4 - Market Data'!J18) -> 13805.518 | D17: =IF('Step 4 - Market Data'!F18="","",'Step 4 - Market Data'!F18) -> 8612.718 | E17: 4640 | F17: 1533 | G17: 1561 | H17: 207 | I17: -27 | J17: 586 | K17: 4900 | L17: 1640 | M17: =IF($C17="","",IF(OR($E17="",$E17<=0),"NM",$C17/$E17)) -> 2.9753272 | N17: =IF($C17="","",IF(OR($F17="",$F17<=0),"NM",$C17/$F17)) -> 9.0055564 | O17: =IF($C17="","",IF(OR($G17="",$G17<=0),"NM",$C17/$G17)) -> 8.8440218 | P17: =IF($C17="","",IF(OR($H17="",$H17<=0),"NM",$C17/$H17)) -> 66.693324 | Q17: =IF($D17="","",IF(OR($I17="",$I17<=0),"NM",$D17/$I17)) -> NM | R17: =IF($C17="","",IF(OR($J17="",$J17<=0),"NM",$C17/$J17)) -> 23.558904 | S17: =IF($C17="","",IF(OR($K17="",$K17<=0),"NM",$C17/$K17)) -> 2.8174527 | T17: =IF($C17="","",IF(OR($L17="",$L17<=0),"NM",$C17/$L17)) -> 8.4179988 | U17: =IF(OR($E17="",$K17=""),"",IF($E17<=0,"NM",$K17/$E17-1)) -> 0.056034483 | V17: =IF(OR($E17="",$F17=""),"",IF($E17<=0,"NM",$F17/$E17)) -> 0.33038793 | W17: =IF(OR($E17="",$G17=""),"",IF($E17<=0,"NM",$G17/$E17)) -> 0.33642241 | X17: =IF(OR($E17="",$H17=""),"",IF($E17<=0,"NM",$H17/$E17)) -> 0.044612069 | Y17: =IF(OR($E17="",$J17=""),"",IF($E17<=0,"NM",$J17/$E17)) -> 0.1262931
A19: Minimum | M19: {=IFERROR(MIN(IF(B8:B17="Yes",M8:M17)),"")} -> 2.9753272 | N19: {=IFERROR(MIN(IF(B8:B17="Yes",N8:N17)),"")} -> 9.0055564 | O19: {=IFERROR(MIN(IF(B8:B17="Yes",O8:O17)),"")} -> 8.8440218 | P19: {=IFERROR(MIN(IF(B8:B17="Yes",P8:P17)),"")} -> 22.893502 | Q19: {=IFERROR(MIN(IF(B8:B17="Yes",Q8:Q17)),"")} -> 28.33501 | R19: {=IFERROR(MIN(IF(B8:B17="Yes",R8:R17)),"")} -> 19.992801 | S19: {=IFERROR(MIN(IF(B8:B17="Yes",S8:S17)),"")} -> 2.8174527 | T19: {=IFERROR(MIN(IF(B8:B17="Yes",T8:T17)),"")} -> 8.4179988
A20: 25th percentile | M20: {=IFERROR(QUARTILE(IF(B8:B17="Yes",M8:M17),1),"")} -> 7.0795242 | N20: {=IFERROR(QUARTILE(IF(B8:B17="Yes",N8:N17),1),"")} -> 31.478106 | O20: {=IFERROR(QUARTILE(IF(B8:B17="Yes",O8:O17),1),"")} -> 12.590878 | P20: {=IFERROR(QUARTILE(IF(B8:B17="Yes",P8:P17),1),"")} -> 33.843457 | Q20: {=IFERROR(QUARTILE(IF(B8:B17="Yes",Q8:Q17),1),"")} -> 28.33501 | R20: {=IFERROR(QUARTILE(IF(B8:B17="Yes",R8:R17),1),"")} -> 20.884327 | S20: {=IFERROR(QUARTILE(IF(B8:B17="Yes",S8:S17),1),"")} -> 3.3947571 | T20: {=IFERROR(QUARTILE(IF(B8:B17="Yes",T8:T17),1),"")} -> 14.83583
A21: Median | M21: {=IFERROR(QUARTILE(IF(B8:B17="Yes",M8:M17),2),"")} -> 18.258269 | N21: {=IFERROR(QUARTILE(IF(B8:B17="Yes",N8:N17),2),"")} -> 73.530626 | O21: {=IFERROR(QUARTILE(IF(B8:B17="Yes",O8:O17),2),"")} -> 16.337734 | P21: {=IFERROR(QUARTILE(IF(B8:B17="Yes",P8:P17),2),"")} -> 44.793413 | Q21: {=IFERROR(QUARTILE(IF(B8:B17="Yes",Q8:Q17),2),"")} -> 28.33501 | R21: {=IFERROR(QUARTILE(IF(B8:B17="Yes",R8:R17),2),"")} -> 21.775853 | S21: {=IFERROR(QUARTILE(IF(B8:B17="Yes",S8:S17),2),"")} -> 7.7599321 | T21: {=IFERROR(QUARTILE(IF(B8:B17="Yes",T8:T17),2),"")} -> 129.85195
A22: 75th percentile | M22: {=IFERROR(QUARTILE(IF(B8:B17="Yes",M8:M17),3),"")} -> 57.53786 | N22: {=IFERROR(QUARTILE(IF(B8:B17="Yes",N8:N17),3),"")} -> 189.09108 | O22: {=IFERROR(QUARTILE(IF(B8:B17="Yes",O8:O17),3),"")} -> 372.46738 | P22: {=IFERROR(QUARTILE(IF(B8:B17="Yes",P8:P17),3),"")} -> 55.743368 | Q22: {=IFERROR(QUARTILE(IF(B8:B17="Yes",Q8:Q17),3),"")} -> 28.33501 | R22: {=IFERROR(QUARTILE(IF(B8:B17="Yes",R8:R17),3),"")} -> 22.667379 | S22: {=IFERROR(QUARTILE(IF(B8:B17="Yes",S8:S17),3),"")} -> 46.843806 | T22: {=IFERROR(QUARTILE(IF(B8:B17="Yes",T8:T17),3),"")} -> 276.76421
A23: Maximum | M23: {=IFERROR(MAX(IF(B8:B17="Yes",M8:M17)),"")} -> 279.06185 | N23: {=IFERROR(MAX(IF(B8:B17="Yes",N8:N17)),"")} -> 477.26876 | O23: {=IFERROR(MAX(IF(B8:B17="Yes",O8:O17)),"")} -> 728.59703 | P23: {=IFERROR(MAX(IF(B8:B17="Yes",P8:P17)),"")} -> 66.693324 | Q23: {=IFERROR(MAX(IF(B8:B17="Yes",Q8:Q17)),"")} -> 28.33501 | R23: {=IFERROR(MAX(IF(B8:B17="Yes",R8:R17)),"")} -> 23.558904 | S23: {=IFERROR(MAX(IF(B8:B17="Yes",S8:S17)),"")} -> 135.54433 | T23: {=IFERROR(MAX(IF(B8:B17="Yes",T8:T17)),"")} -> 378.87046
A25: Operating ratios (grey) describe each peer’s growth and profitability — use them to sanity-check comparability and to explain differences in multiples (faster growth usually = higher revenue multiple).

Sheet Step 6 - Select Multiples
A1: Step 6 — Select the Most Relevant Multiples
A2: The ‘Auto guidance’ reacts to your peer set and SpaceX’s profile. Treat it as a nudge — you decide what to use.
A4: For each multiple, the sheet checks two things automatically: (1) how many of your peers produce a MEANINGFUL value (not NM), and (2) whether SpaceX’s own metric is positive. From that it suggests Recommended / Caution / Avoid. You make the final Yes/No call and say why.
A6: ▶ YOUR TURN: Read the guidance, then mark Use it? Yes or No and give your reason.
A7: Multiple | B7: What it measures | C7: # peers meaningful | D7: Peer median | E7: SpaceX metric | F7: Auto guidance | G7: Use it? (Yes/No) | H7: Your rationale
A8: TEV / Revenue (LTM) | B8: Sales-based; good for high-growth, unprofitable firms | C8: =COUNTIFS('Step 5 - Multiples & Ratios'!$B$7:$B$17,"Yes",'Step 5 - Multiples & Ratios'!M$7:M$17,"<>NM") -> 7 | D8: =IF('Step 5 - Multiples & Ratios'!M21="","",'Step 5 - Multiples & Ratios'!M21) -> 18.258269 | E8: =IF('Step 2 - SpaceX Snapshot'!B12="","",'Step 2 - SpaceX Snapshot'!B12) -> 19301 | F8: =IF(COUNT('Step 5 - Multiples & Ratios'!C$7:C$17)=0,"Add peer data first",IF('Step 2 - SpaceX Snapshot'!B12="","Enter SpaceX metric",IF('Step 2 - SpaceX Snapshot'!B12<=0,"Avoid – SpaceX metric negative",IF(COUNT('Step 5 - Multiples & Ratios'!M$7:M$17)=0,"Avoid – no peers meaningful",IF(COUNT('Step 5 - Multiples & Ratios'!M$7:M$17)/COUNT('Step 5 - Multiples & Ratios'!C$7:C$17)<0.5,"Caution – few peers meaningful","Recommended"))))) -> Recommended | G8: Yes | H8: 8 meaningful peers; relates well to SpaceX's scale/profitability
A9: TEV / Gross Profit (LTM) | B9: Adjusts for differing cost structures | C9: =COUNTIFS('Step 5 - Multiples & Ratios'!$B$7:$B$17,"Yes",'Step 5 - Multiples & Ratios'!N$7:N$17,"<>NM") -> 7 | D9: =IF('Step 5 - Multiples & Ratios'!N21="","",'Step 5 - Multiples & Ratios'!N21) -> 73.530626 | E9: =IF('Step 2 - SpaceX Snapshot'!B13="","",'Step 2 - SpaceX Snapshot'!B13) -> 9424 | F9: =IF(COUNT('Step 5 - Multiples & Ratios'!C$7:C$17)=0,"Add peer data first",IF('Step 2 - SpaceX Snapshot'!B13="","Enter SpaceX metric",IF('Step 2 - SpaceX Snapshot'!B13<=0,"Avoid – SpaceX metric negative",IF(COUNT('Step 5 - Multiples & Ratios'!N$7:N$17)=0,"Avoid – no peers meaningful",IF(COUNT('Step 5 - Multiples & Ratios'!N$7:N$17)/COUNT('Step 5 - Multiples & Ratios'!C$7:C$17)<0.5,"Caution – few peers meaningful","Recommended"))))) -> Recommended | G9: No | H9: Median is thrown off by smaller peers
A10: TEV / EBITDA (LTM) | B10: Cash operating profit; needs positive EBITDA | C10: =COUNTIFS('Step 5 - Multiples & Ratios'!$B$7:$B$17,"Yes",'Step 5 - Multiples & Ratios'!O$7:O$17,"<>NM") -> 3 | D10: =IF('Step 5 - Multiples & Ratios'!O21="","",'Step 5 - Multiples & Ratios'!O21) -> 16.337734 | E10: =IF('Step 2 - SpaceX Snapshot'!B14="","",'Step 2 - SpaceX Snapshot'!B14) -> 1299 | F10: =IF(COUNT('Step 5 - Multiples & Ratios'!C$7:C$17)=0,"Add peer data first",IF('Step 2 - SpaceX Snapshot'!B14="","Enter SpaceX metric",IF('Step 2 - SpaceX Snapshot'!B14<=0,"Avoid – SpaceX metric negative",IF(COUNT('Step 5 - Multiples & Ratios'!O$7:O$17)=0,"Avoid – no peers meaningful",IF(COUNT('Step 5 - Multiples & Ratios'!O$7:O$17)/COUNT('Step 5 - Multiples & Ratios'!C$7:C$17)<0.5,"Caution – few peers meaningful","Recommended"))))) -> Recommended | G10: No | H10: Only 4 peers are positive
A11: TEV / EBIT (LTM) | B11: Operating profit; needs positive EBIT | C11: =COUNTIFS('Step 5 - Multiples & Ratios'!$B$7:$B$17,"Yes",'Step 5 - Multiples & Ratios'!P$7:P$17,"<>NM") -> 2 | D11: =IF('Step 5 - Multiples & Ratios'!P21="","",'Step 5 - Multiples & Ratios'!P21) -> 44.793413 | E11: =IF('Step 2 - SpaceX Snapshot'!B15="","",'Step 2 - SpaceX Snapshot'!B15) -> -6401 | F11: =IF(COUNT('Step 5 - Multiples & Ratios'!C$7:C$17)=0,"Add peer data first",IF('Step 2 - SpaceX Snapshot'!B15="","Enter SpaceX metric",IF('Step 2 - SpaceX Snapshot'!B15<=0,"Avoid – SpaceX metric negative",IF(COUNT('Step 5 - Multiples & Ratios'!P$7:P$17)=0,"Avoid – no peers meaningful",IF(COUNT('Step 5 - Multiples & Ratios'!P$7:P$17)/COUNT('Step 5 - Multiples & Ratios'!C$7:C$17)<0.5,"Caution – few peers meaningful","Recommended"))))) -> Avoid – SpaceX metric negative | G11: No | H11: SpaceX has a negative EBIT
A12: P / E (LTM) | B12: Needs positive net income | C12: =COUNT('Step 5 - Multiples & Ratios'!Q$7:Q$17) -> 3 | D12: =IF('Step 5 - Multiples & Ratios'!Q21="","",'Step 5 - Multiples & Ratios'!Q21) -> 28.33501 | E12: =IF('Step 2 - SpaceX Snapshot'!B16="","",'Step 2 - SpaceX Snapshot'!B16) -> -6792 | F12: =IF(COUNT('Step 5 - Multiples & Ratios'!C$7:C$17)=0,"Add peer data first",IF('Step 2 - SpaceX Snapshot'!B16="","Enter SpaceX metric",IF('Step 2 - SpaceX Snapshot'!B16<=0,"Avoid – SpaceX metric negative",IF(COUNT('Step 5 - Multiples & Ratios'!Q$7:Q$17)=0,"Avoid – no peers meaningful",IF(COUNT('Step 5 - Multiples & Ratios'!Q$7:Q$17)/COUNT('Step 5 - Multiples & Ratios'!C$7:C$17)<0.5,"Caution – few peers meaningful","Recommended"))))) -> Avoid – SpaceX metric negative | G12: No | H12: SpaceX has a negative net income
A13: TEV / FCF (LTM) | B13: Needs positive free cash flow | C13: =COUNTIFS('Step 5 - Multiples & Ratios'!$B$7:$B$17,"Yes",'Step 5 - Multiples & Ratios'!R$7:R$17,"<>NM") -> 2 | D13: =IF('Step 5 - Multiples & Ratios'!R21="","",'Step 5 - Multiples & Ratios'!R21) -> 21.775853 | E13: =IF('Step 2 - SpaceX Snapshot'!B17="","",'Step 2 - SpaceX Snapshot'!B17) -> -21629 | F13: =IF(COUNT('Step 5 - Multiples & Ratios'!C$7:C$17)=0,"Add peer data first",IF('Step 2 - SpaceX Snapshot'!B17="","Enter SpaceX metric",IF('Step 2 - SpaceX Snapshot'!B17<=0,"Avoid – SpaceX metric negative",IF(COUNT('Step 5 - Multiples & Ratios'!R$7:R$17)=0,"Avoid – no peers meaningful",IF(COUNT('Step 5 - Multiples & Ratios'!R$7:R$17)/COUNT('Step 5 - Multiples & Ratios'!C$7:C$17)<0.5,"Caution – few peers meaningful","Recommended"))))) -> Avoid – SpaceX metric negative | G13: No | H13: SpaceX has a negative FCF
A14: TEV / Revenue (FY+1) | B14: Forward sales; needs your FY+1 estimate | C14: =COUNTIFS('Step 5 - Multiples & Ratios'!$B$7:$B$17,"Yes",'Step 5 - Multiples & Ratios'!S$7:S$17,"<>NM") -> 7 | D14: =IF('Step 5 - Multiples & Ratios'!S21="","",'Step 5 - Multiples & Ratios'!S21) -> 7.7599321 | E14: 23903 | F14: =IF(COUNT('Step 5 - Multiples & Ratios'!C$7:C$17)=0,"Add peer data first",IF('Step 2 - SpaceX Snapshot'!B20="","Enter SpaceX metric",IF('Step 2 - SpaceX Snapshot'!B20<=0,"Avoid – SpaceX metric negative",IF(COUNT('Step 5 - Multiples & Ratios'!S$7:S$17)=0,"Avoid – no peers meaningful",IF(COUNT('Step 5 - Multiples & Ratios'!S$7:S$17)/COUNT('Step 5 - Multiples & Ratios'!C$7:C$17)<0.5,"Caution – few peers meaningful","Recommended"))))) -> Recommended | G14: Yes | H14: all 8 peers have meaningful multiples
A15: TEV / EBITDA (FY+1) | B15: Forward EBITDA; needs your FY+1 estimate | C15: =COUNTIFS('Step 5 - Multiples & Ratios'!$B$7:$B$17,"Yes",'Step 5 - Multiples & Ratios'!T$7:T$17,"<>NM") -> 4 | D15: =IF('Step 5 - Multiples & Ratios'!T21="","",'Step 5 - Multiples & Ratios'!T21) -> 129.85195 | E15: 7405 | F15: =IF(COUNT('Step 5 - Multiples & Ratios'!C$7:C$17)=0,"Add peer data first",IF('Step 2 - SpaceX Snapshot'!B21="","Enter SpaceX metric",IF('Step 2 - SpaceX Snapshot'!B21<=0,"Avoid – SpaceX metric negative",IF(COUNT('Step 5 - Multiples & Ratios'!T$7:T$17)=0,"Avoid – no peers meaningful",IF(COUNT('Step 5 - Multiples & Ratios'!T$7:T$17)/COUNT('Step 5 - Multiples & Ratios'!C$7:C$17)<0.5,"Caution – few peers meaningful","Recommended"))))) -> Recommended | G15: Yes | H15: A good forward probability anchor; 5 meaningful peers; reflects market growth expectations
A17: Why this matters: SpaceX has negative EBIT, net income and FCF, so those multiples will read ‘Avoid’. If your peer set is mostly unprofitable too, even TEV/EBITDA may show ‘Caution’ because few peers give a meaningful number. That’s exactly why revenue-based multiples usually win for a company like this — but the decision, and the rationale, are yours.

Sheet Step 7 - Apply to SpaceX
A1: Step 7 — Apply Your Selected Multiples to SpaceX ($mm, except per-share)
A2: Only the multiples you marked Use = Yes produce a value. Low / Base / High use the peer 25th / median / 75th percentile.
A4: Implied enterprise value = SpaceX metric × peer multiple. For TEV multiples we then subtract net debt to get equity value; for P/E we use net income × P/E directly. Equity value ÷ diluted shares = implied price per share.
A6: Multiple | B6: Use? | C6: SpaceX metric | D6: Peer 25th | E6: Peer median | F6: Peer 75th | G6: Equity – Low | H6: Equity – Base | I6: Equity – High | J6: Price – Low | K6: Price – Base | L6: Price – High
A7: TEV / Revenue (LTM) | B7: =IF('Step 6 - Select Multiples'!G8="","",'Step 6 - Select Multiples'!G8) -> Yes | C7: =IF('Step 2 - SpaceX Snapshot'!B12="","",'Step 2 - SpaceX Snapshot'!B12) -> 19301 | D7: =IF('Step 5 - Multiples & Ratios'!M20="","",'Step 5 - Multiples & Ratios'!M20) -> 7.0795242 | E7: =IF('Step 5 - Multiples & Ratios'!M21="","",'Step 5 - Multiples & Ratios'!M21) -> 18.258269 | F7: =IF('Step 5 - Multiples & Ratios'!M22="","",'Step 5 - Multiples & Ratios'!M22) -> 57.53786 | G7: =IF(AND($B7="Yes",ISNUMBER($C7),ISNUMBER($D7)),$C7*$D7-'Step 2 - SpaceX Snapshot'!B18,"") -> 129713.9 | H7: =IF(AND($B7="Yes",ISNUMBER($C7),ISNUMBER($E7)),$C7*$E7-'Step 2 - SpaceX Snapshot'!B18,"") -> 345474.84 | I7: =IF(AND($B7="Yes",ISNUMBER($C7),ISNUMBER($F7)),$C7*$F7-'Step 2 - SpaceX Snapshot'!B18,"") -> 1103610.2 | J7: =IF(AND(ISNUMBER($G7),'Step 2 - SpaceX Snapshot'!B19>0),$G7/'Step 2 - SpaceX Snapshot'!B19,"") -> 9.9200741 | K7: =IF(AND(ISNUMBER($H7),'Step 2 - SpaceX Snapshot'!B19>0),$H7/'Step 2 - SpaceX Snapshot'!B19,"") -> 26.420732 | L7: =IF(AND(ISNUMBER($I7),'Step 2 - SpaceX Snapshot'!B19>0),$I7/'Step 2 - SpaceX Snapshot'!B19,"") -> 84.400328
A8: TEV / Gross Profit (LTM) | B8: yes | C8: =IF('Step 2 - SpaceX Snapshot'!B13="","",'Step 2 - SpaceX Snapshot'!B13) -> 9424 | D8: =IF('Step 5 - Multiples & Ratios'!N20="","",'Step 5 - Multiples & Ratios'!N20) -> 31.478106 | E8: =IF('Step 5 - Multiples & Ratios'!N21="","",'Step 5 - Multiples & Ratios'!N21) -> 73.530626 | F8: =IF('Step 5 - Multiples & Ratios'!N22="","",'Step 5 - Multiples & Ratios'!N22) -> 189.09108 | G8: =IF(AND($B8="Yes",ISNUMBER($C8),ISNUMBER($D8)),$C8*$D8-'Step 2 - SpaceX Snapshot'!B18,"") -> 289721.67 | H8: =IF(AND($B8="Yes",ISNUMBER($C8),ISNUMBER($E8)),$C8*$E8-'Step 2 - SpaceX Snapshot'!B18,"") -> 686024.62 | I8: =IF(AND($B8="Yes",ISNUMBER($C8),ISNUMBER($F8)),$C8*$F8-'Step 2 - SpaceX Snapshot'!B18,"") -> 1775066.4 | J8: =IF(AND(ISNUMBER($G8),'Step 2 - SpaceX Snapshot'!B19>0),$G8/'Step 2 - SpaceX Snapshot'!B19,"") -> 22.15692 | K8: =IF(AND(ISNUMBER($H8),'Step 2 - SpaceX Snapshot'!B19>0),$H8/'Step 2 - SpaceX Snapshot'!B19,"") -> 52.464811 | L8: =IF(AND(ISNUMBER($I8),'Step 2 - SpaceX Snapshot'!B19>0),$I8/'Step 2 - SpaceX Snapshot'!B19,"") -> 135.75099
A9: TEV / EBITDA (LTM) | B9: =IF('Step 6 - Select Multiples'!G10="","",'Step 6 - Select Multiples'!G10) -> No | C9: =IF('Step 2 - SpaceX Snapshot'!B14="","",'Step 2 - SpaceX Snapshot'!B14) -> 1299 | D9: =IF('Step 5 - Multiples & Ratios'!O20="","",'Step 5 - Multiples & Ratios'!O20) -> 12.590878 | E9: =IF('Step 5 - Multiples & Ratios'!O21="","",'Step 5 - Multiples & Ratios'!O21) -> 16.337734 | F9: =IF('Step 5 - Multiples & Ratios'!O22="","",'Step 5 - Multiples & Ratios'!O22) -> 372.46738 | G9: =IF(AND($B9="Yes",ISNUMBER($C9),ISNUMBER($D9)),$C9*$D9-'Step 2 - SpaceX Snapshot'!B18,"") | H9: =IF(AND($B9="Yes",ISNUMBER($C9),ISNUMBER($E9)),$C9*$E9-'Step 2 - SpaceX Snapshot'!B18,"") | I9: =IF(AND($B9="Yes",ISNUMBER($C9),ISNUMBER($F9)),$C9*$F9-'Step 2 - SpaceX Snapshot'!B18,"") | J9: =IF(AND(ISNUMBER($G9),'Step 2 - SpaceX Snapshot'!B19>0),$G9/'Step 2 - SpaceX Snapshot'!B19,"") | K9: =IF(AND(ISNUMBER($H9),'Step 2 - SpaceX Snapshot'!B19>0),$H9/'Step 2 - SpaceX Snapshot'!B19,"") | L9: =IF(AND(ISNUMBER($I9),'Step 2 - SpaceX Snapshot'!B19>0),$I9/'Step 2 - SpaceX Snapshot'!B19,"")
A10: TEV / EBIT (LTM) | B10: =IF('Step 6 - Select Multiples'!G11="","",'Step 6 - Select Multiples'!G11) -> No | C10: =IF('Step 2 - SpaceX Snapshot'!B15="","",'Step 2 - SpaceX Snapshot'!B15) -> -6401 | D10: =IF('Step 5 - Multiples & Ratios'!P20="","",'Step 5 - Multiples & Ratios'!P20) -> 33.843457 | E10: =IF('Step 5 - Multiples & Ratios'!P21="","",'Step 5 - Multiples & Ratios'!P21) -> 44.793413 | F10: =IF('Step 5 - Multiples & Ratios'!P22="","",'Step 5 - Multiples & Ratios'!P22) -> 55.743368 | G10: =IF(AND($B10="Yes",ISNUMBER($C10),ISNUMBER($D10)),$C10*$D10-'Step 2 - SpaceX Snapshot'!B18,"") | H10: =IF(AND($B10="Yes",ISNUMBER($C10),ISNUMBER($E10)),$C10*$E10-'Step 2 - SpaceX Snapshot'!B18,"") | I10: =IF(AND($B10="Yes",ISNUMBER($C10),ISNUMBER($F10)),$C10*$F10-'Step 2 - SpaceX Snapshot'!B18,"") | J10: =IF(AND(ISNUMBER($G10),'Step 2 - SpaceX Snapshot'!B19>0),$G10/'Step 2 - SpaceX Snapshot'!B19,"") | K10: =IF(AND(ISNUMBER($H10),'Step 2 - SpaceX Snapshot'!B19>0),$H10/'Step 2 - SpaceX Snapshot'!B19,"") | L10: =IF(AND(ISNUMBER($I10),'Step 2 - SpaceX Snapshot'!B19>0),$I10/'Step 2 - SpaceX Snapshot'!B19,"")
A11: P / E (LTM) | B11: =IF('Step 6 - Select Multiples'!G12="","",'Step 6 - Select Multiples'!G12) -> No | C11: =IF('Step 2 - SpaceX Snapshot'!B16="","",'Step 2 - SpaceX Snapshot'!B16) -> -6792 | D11: =IF('Step 5 - Multiples & Ratios'!Q20="","",'Step 5 - Multiples & Ratios'!Q20) -> 28.33501 | E11: =IF('Step 5 - Multiples & Ratios'!Q21="","",'Step 5 - Multiples & Ratios'!Q21) -> 28.33501 | F11: =IF('Step 5 - Multiples & Ratios'!Q22="","",'Step 5 - Multiples & Ratios'!Q22) -> 28.33501 | G11: =IF(AND($B11="Yes",ISNUMBER($C11),ISNUMBER($D11)),$C11*$D11,"") | H11: =IF(AND($B11="Yes",ISNUMBER($C11),ISNUMBER($E11)),$C11*$E11,"") | I11: =IF(AND($B11="Yes",ISNUMBER($C11),ISNUMBER($F11)),$C11*$F11,"") | J11: =IF(AND(ISNUMBER($G11),'Step 2 - SpaceX Snapshot'!B19>0),$G11/'Step 2 - SpaceX Snapshot'!B19,"") | K11: =IF(AND(ISNUMBER($H11),'Step 2 - SpaceX Snapshot'!B19>0),$H11/'Step 2 - SpaceX Snapshot'!B19,"") | L11: =IF(AND(ISNUMBER($I11),'Step 2 - SpaceX Snapshot'!B19>0),$I11/'Step 2 - SpaceX Snapshot'!B19,"")
A12: TEV / FCF (LTM) | B12: =IF('Step 6 - Select Multiples'!G13="","",'Step 6 - Select Multiples'!G13) -> No | C12: =IF('Step 2 - SpaceX Snapshot'!B17="","",'Step 2 - SpaceX Snapshot'!B17) -> -21629 | D12: =IF('Step 5 - Multiples & Ratios'!R20="","",'Step 5 - Multiples & Ratios'!R20) -> 20.884327 | E12: =IF('Step 5 - Multiples & Ratios'!R21="","",'Step 5 - Multiples & Ratios'!R21) -> 21.775853 | F12: =IF('Step 5 - Multiples & Ratios'!R22="","",'Step 5 - Multiples & Ratios'!R22) -> 22.667379 | G12: =IF(AND($B12="Yes",ISNUMBER($C12),ISNUMBER($D12)),$C12*$D12-'Step 2 - SpaceX Snapshot'!B18,"") | H12: =IF(AND($B12="Yes",ISNUMBER($C12),ISNUMBER($E12)),$C12*$E12-'Step 2 - SpaceX Snapshot'!B18,"") | I12: =IF(AND($B12="Yes",ISNUMBER($C12),ISNUMBER($F12)),$C12*$F12-'Step 2 - SpaceX Snapshot'!B18,"") | J12: =IF(AND(ISNUMBER($G12),'Step 2 - SpaceX Snapshot'!B19>0),$G12/'Step 2 - SpaceX Snapshot'!B19,"") | K12: =IF(AND(ISNUMBER($H12),'Step 2 - SpaceX Snapshot'!B19>0),$H12/'Step 2 - SpaceX Snapshot'!B19,"") | L12: =IF(AND(ISNUMBER($I12),'Step 2 - SpaceX Snapshot'!B19>0),$I12/'Step 2 - SpaceX Snapshot'!B19,"")
A13: TEV / Revenue (FY+1) | B13: =IF('Step 6 - Select Multiples'!G14="","",'Step 6 - Select Multiples'!G14) -> Yes | C13: 23904 | D13: =IF('Step 5 - Multiples & Ratios'!S20="","",'Step 5 - Multiples & Ratios'!S20) -> 3.3947571 | E13: =IF('Step 5 - Multiples & Ratios'!S21="","",'Step 5 - Multiples & Ratios'!S21) -> 7.7599321 | F13: =IF('Step 5 - Multiples & Ratios'!S22="","",'Step 5 - Multiples & Ratios'!S22) -> 46.843806 | G13: =IF(AND($B13="Yes",ISNUMBER($C13),ISNUMBER($D13)),$C13*$D13-'Step 2 - SpaceX Snapshot'!B18,"") -> 74220.274 | H13: =IF(AND($B13="Yes",ISNUMBER($C13),ISNUMBER($E13)),$C13*$E13-'Step 2 - SpaceX Snapshot'!B18,"") -> 178565.42 | I13: =IF(AND($B13="Yes",ISNUMBER($C13),ISNUMBER($F13)),$C13*$F13-'Step 2 - SpaceX Snapshot'!B18,"") -> 1112826.3 | J13: =IF(AND(ISNUMBER($G13),'Step 2 - SpaceX Snapshot'!B19>0),$G13/'Step 2 - SpaceX Snapshot'!B19,"") -> 5.6761121 | K13: =IF(AND(ISNUMBER($H13),'Step 2 - SpaceX Snapshot'!B19>0),$H13/'Step 2 - SpaceX Snapshot'!B19,"") -> 13.656071 | L13: =IF(AND(ISNUMBER($I13),'Step 2 - SpaceX Snapshot'!B19>0),$I13/'Step 2 - SpaceX Snapshot'!B19,"") -> 85.105142
A14: TEV / EBITDA (FY+1) | B14: =IF('Step 6 - Select Multiples'!G15="","",'Step 6 - Select Multiples'!G15) -> Yes | C14: 7405 | D14: =IF('Step 5 - Multiples & Ratios'!T20="","",'Step 5 - Multiples & Ratios'!T20) -> 14.83583 | E14: =IF('Step 5 - Multiples & Ratios'!T21="","",'Step 5 - Multiples & Ratios'!T21) -> 129.85195 | F14: =IF('Step 5 - Multiples & Ratios'!T22="","",'Step 5 - Multiples & Ratios'!T22) -> 276.76421 | G14: =IF(AND($B14="Yes",ISNUMBER($C14),ISNUMBER($D14)),$C14*$D14-'Step 2 - SpaceX Snapshot'!B18,"") -> 102931.32 | H14: =IF(AND($B14="Yes",ISNUMBER($C14),ISNUMBER($E14)),$C14*$E14-'Step 2 - SpaceX Snapshot'!B18,"") -> 954625.72 | I14: =IF(AND($B14="Yes",ISNUMBER($C14),ISNUMBER($F14)),$C14*$F14-'Step 2 - SpaceX Snapshot'!B18,"") -> 2042511 | J14: =IF(AND(ISNUMBER($G14),'Step 2 - SpaceX Snapshot'!B19>0),$G14/'Step 2 - SpaceX Snapshot'!B19,"") -> 7.8718347 | K14: =IF(AND(ISNUMBER($H14),'Step 2 - SpaceX Snapshot'!B19>0),$H14/'Step 2 - SpaceX Snapshot'!B19,"") -> 73.006502 | L14: =IF(AND(ISNUMBER($I14),'Step 2 - SpaceX Snapshot'!B19>0),$I14/'Step 2 - SpaceX Snapshot'!B19,"") -> 156.20424
A16: Rows with ‘Avoid’ metrics (negative EBIT, net income, FCF) will stay blank even if you set Use = Yes, because the math isn’t meaningful — another built-in guardrail. The active rows feed your range in Step 8.

Sheet Step 8 - Valuation Range
A1: Step 8 — Build a Valuation Range ($mm, except per-share)
A2: Combine your selected methods into a low–base–high range, then compare to the IPO price.
A4: Low = the lowest of your methods’ low estimates. Base = the average of the methods’ base estimates. High = the highest of the high estimates. This spans the methods you chose — a range, not a single ‘right’ number.
B6: Low | C6: Base | D6: High
A7: Implied equity value | B7: =IF(COUNT('Step 7 - Apply to SpaceX'!G7:G14)=0,"",MIN('Step 7 - Apply to SpaceX'!G7:G14)) -> 74220.274 | C7: =IF(COUNT('Step 7 - Apply to SpaceX'!H7:H14)=0,"",AVERAGE('Step 7 - Apply to SpaceX'!H7:H14)) -> 541172.65 | D7: =IF(COUNT('Step 7 - Apply to SpaceX'!I7:I14)=0,"",MAX('Step 7 - Apply to SpaceX'!I7:I14)) -> 2042511
A8: Implied price per share | B8: =IF(COUNT('Step 7 - Apply to SpaceX'!J7:J14)=0,"",MIN('Step 7 - Apply to SpaceX'!J7:J14)) -> 5.6761121 | C8: =IF(COUNT('Step 7 - Apply to SpaceX'!K7:K14)=0,"",AVERAGE('Step 7 - Apply to SpaceX'!K7:K14)) -> 41.387029 | D8: =IF(COUNT('Step 7 - Apply to SpaceX'!L7:L14)=0,"",MAX('Step 7 - Apply to SpaceX'!L7:L14)) -> 156.20424
A9: Memo: IPO offer price | B9: ='Step 2 - SpaceX Snapshot'!B27 -> 135 | C9: ='Step 2 - SpaceX Snapshot'!B27 -> 135 | D9: ='Step 2 - SpaceX Snapshot'!B27 -> 135
A11: Sanity check: how does your range compare to the $135 IPO price? If SpaceX is priced well above your peer-based range, ask why — unique scale, growth, optionality (Starship, future infrastructure), or simply a richer market. There’s rarely one perfect answer; the point is a defensible range and a clear explanation.

Sheet Step 9 - Conclusion
A1: Step 9 — Conclusion & Key Caveats
A2: Write it up in your own words. This is what you’d actually present.
A4: 1. Your valuation conclusion
A5: State your implied range (equity value and price per share) and your single best estimate, if you have one.
B6: The base case is roughly $9-$21 per share centered around $13.43.
A11: 2. Which multiples drove it
A12: Which multiples did you rely on, and why are they the right ones for SpaceX?
A18: 3. What you excluded and why
A19: Which multiples or peers did you drop (e.g., negative-earnings multiples, private companies)?
A25: 4. Comparison to the IPO price
A26: How does your range compare to $135? Explain any gap.
B27: The actual IPO pis priced at $135 which is about 6-10x our base analysis implied value.
A32: 5. Key caveats & risks
A33: Where could this be most wrong? (peer comparability, segment mix, optionality, forward estimates, data quality)
B34: A key risk and gap is present on the facture that a public comp can't fully grasp the scale of Starlink along with xAI. There's not necessarily a company that fits well with SpaceX.
A39: 6. What would change your view
A40: What new information or analysis (e.g., a sum-of-the-parts) would most improve the answer?

Sheet Glossary
A1: Glossary
A2: Key terms in plain language.
B4: Term | C4: Definition
B5: Comps | C5: Comparable-companies analysis — valuing a company against similar public companies.
B6: Peer | C6: A public company similar enough to be valued on similar terms.
B7: Multiple | C7: Value ÷ a financial metric (e.g. TEV ÷ revenue); lets you compare different-sized companies.
B8: Equity Value / Market Cap | C8: Value of the shares = share price × diluted shares.
B9: Enterprise Value (TEV) | C9: Value of the whole business = market cap + debt + preferred + minority − cash.
B10: Net Debt | C10: Total debt − cash. Negative means more cash than debt (net cash).
B11: EBITDA | C11: Earnings before interest, taxes, depreciation & amortization; a proxy for operating cash profit.
B12: EBIT | C12: Operating profit (earnings before interest and taxes).
B13: Net Income | C13: Bottom-line profit after all costs, interest and taxes.
B14: FCF (Free Cash Flow) | C14: Operating cash flow − capital expenditures.
B15: Gross Profit | C15: Revenue − direct cost of the product/service.
... B23: IPO | C23: Initial Public Offering — a company’s first sale of shares to the public.
